bojango/__init__.py
bojango/action/__init__.py
bojango/action/dispatcher.py
bojango/action/exceptions.py
bojango/action/screen.py
bojango/action/behaviors/__init__.py
bojango/action/behaviors/base.py
bojango/action/behaviors/screen_behaviors.py
bojango/action/strategies/__init__.py
bojango/action/strategies/base.py
bojango/action/strategies/content_strategies.py
bojango/core/__init__.py
bojango/core/bot.py
bojango/core/routing.py
bojango/core/utils.py
bojango/extensions/__init__.py
bojango/utils/__init__.py
bojango/utils/formatter.py
bojango/utils/localization.py
bojango/utils/format/__init__.py
bojango/utils/format/base.py
bojango/utils/format/default_formatters.py
bojango/utils/format/openai_formatter.py
bojango-1.1.22.dist-info/LICENSE
bojango-1.1.22.dist-info/METADATA
bojango-1.1.22.dist-info/WHEEL
bojango-1.1.22.dist-info/top_level.txt
bojango-1.1.22.dist-info/RECORD
