Metadata-Version: 2.2
Name: bojango
Version: 1.1.22
Summary: A lightweight framework for creating Telegram bots with advanced routing and localization.
Home-page: https://github.com/hugant/bojango
Author: Mironov Daniil
Author-email: hugantmirron@gmail.com
Classifier: Development Status :: 4 - Beta
Classifier: Intended Audience :: Developers
Classifier: License :: OSI Approved :: MIT License
Classifier: Programming Language :: Python :: 3
Classifier: Programming Language :: Python :: 3.9
Classifier: Programming Language :: Python :: 3.10
Requires-Python: >=3.9
License-File: LICENSE
Requires-Dist: python-telegram-bot>=20.0
Requires-Dist: aiologger>=0.6.1
Requires-Dist: aiofiles>=23.1.0
Requires-Dist: polib>=1.1.1
Dynamic: author
Dynamic: author-email
Dynamic: classifier
Dynamic: description
Dynamic: description-content-type
Dynamic: home-page
Dynamic: requires-dist
Dynamic: requires-python
Dynamic: summary
